{
 "SoundBanksInfo": {
  "Platform": "Windows",
  "BasePlatform": "Windows",
  "SchemaVersion": "12",
  "SoundbankVersion": "140",
  "RootPaths": {
   "ProjectRoot": "D:\\Sessions Unreal\\Git\\UEPrototype\\UEPrototype_WwiseProject\\",
   "SourceFilesRoot": "D:\\Sessions Unreal\\Git\\UEPrototype\\UEPrototype_WwiseProject\\.cache\\Windows\\",
   "SoundBanksRoot": "D:\\Sessions Unreal\\Git\\UEPrototype\\UEPrototype_WwiseProject\\GeneratedSoundBanks\\Windows\\",
   "ExternalSourcesInputFile": "",
   "ExternalSourcesOutputRoot": "D:\\Sessions Unreal\\Git\\UEPrototype\\UEPrototype_WwiseProject\\GeneratedSoundBanks\\Windows"
  },
  "SoundBanks": [
   {
    "Id": "2737555487",
    "GUID": "{A32BC81F-C81F-181F-1F1F-1F1F1F1F1F1F}",
    "Language": "SFX",
    "Hash": "2956267315",
    "ObjectPath": "\\SoundBanks\\Default Work Unit\\SB_D7FBE7C30C364EB3AA8FDA518BB8EBD9",
    "ShortName": "SB_D7FBE7C30C364EB3AA8FDA518BB8EBD9",
    "Path": "SB_D7FBE7C30C364EB3AA8FDA518BB8EBD9.bnk",
    "IncludedEvents": [
     {
      "Id": "600623643",
      "Name": "MC_FT_Wet",
      "ObjectPath": "\\Events\\Default Work Unit\\Jules\\MC\\MC_FT_Wet",
      "GUID": "{D7FBE7C3-0C36-4EB3-AA8F-DA518BB8EBD9}",
      "DurationType": "OneShot",
      "DurationMin": "0.197133",
      "DurationMax": "0.300305",
      "ExcludedMemoryFiles": [
       {
        "Id": "35543373",
        "Language": "SFX",
        "ShortName": "MC_FT_WetStep_07.wav",
        "Path": "SFX\\MC_FT_WetStep_07_10C4C929.wem"
       },
       {
        "Id": "333675992",
        "Language": "SFX",
        "ShortName": "MC_FT_WetStep_02.wav",
        "Path": "SFX\\MC_FT_WetStep_02_10C4C929.wem"
       },
       {
        "Id": "339539667",
        "Language": "SFX",
        "ShortName": "MC_FT_WetStep_05.wav",
        "Path": "SFX\\MC_FT_WetStep_05_10C4C929.wem"
       },
       {
        "Id": "381775902",
        "Language": "SFX",
        "ShortName": "MC_FT_WetStep_10.wav",
        "Path": "SFX\\MC_FT_WetStep_10_10C4C929.wem"
       },
       {
        "Id": "615955123",
        "Language": "SFX",
        "ShortName": "MC_FT_WetStep_04.wav",
        "Path": "SFX\\MC_FT_WetStep_04_10C4C929.wem"
       },
       {
        "Id": "807317424",
        "Language": "SFX",
        "ShortName": "MC_FT_WetStep_08.wav",
        "Path": "SFX\\MC_FT_WetStep_08_10C4C929.wem"
       },
       {
        "Id": "922683831",
        "Language": "SFX",
        "ShortName": "MC_FT_WetStep_01.wav",
        "Path": "SFX\\MC_FT_WetStep_01_10C4C929.wem"
       },
       {
        "Id": "938684526",
        "Language": "SFX",
        "ShortName": "MC_FT_WetStep_03.wav",
        "Path": "SFX\\MC_FT_WetStep_03_10C4C929.wem"
       },
       {
        "Id": "950217733",
        "Language": "SFX",
        "ShortName": "MC_FT_WetStep_09.wav",
        "Path": "SFX\\MC_FT_WetStep_09_10C4C929.wem"
       },
       {
        "Id": "1055673814",
        "Language": "SFX",
        "ShortName": "MC_FT_WetStep_06.wav",
        "Path": "SFX\\MC_FT_WetStep_06_10C4C929.wem"
       }
      ]
     }
    ]
   }
  ]
 }
}